{
  "project_info": {
    "project_number": "289654257017",
    "project_id": "maddemo-87a47",
    "storage_bucket": "maddemo-87a47.appspot.com"
  },
  "client": [
    {
      "client_info": {
        "mobilesdk_app_id": "1:289654257017:android:20359f2e1e76987475eba8",
        "android_client_info": {
          "package_name": "au.scottmann.googlesignin"
        }
      },
      "oauth_client": [
        {
          "client_id": "289654257017-ki8qva6ao78m65b8kqijmegq8r1dvmf2.apps.googleusercontent.com",
          "client_type": 1,
          "android_info": {
            "package_name": "au.scottmann.googlesignin",
            "certificate_hash": "3f220b027ff7fae2205ca9f8d0fc6fe474783a81"
          }
        },
        {
          "client_id": "289654257017-9jlnjiqgn96tplctpl0rnkorhskrbih8.apps.googleusercontent.com",
          "client_type": 3
        }
      ],
      "api_key": [
        {
          "current_key": "AIzaSyAVQq0eAyNp09URHcm06k_2yTqjCoHzghs"
        }
      ],
      "services": {
        "appinvite_service": {
          "other_platform_oauth_client": [
            {
              "client_id": "289654257017-79sav079jaba2ovb6c2kuql2fb7m9kb0.apps.googleusercontent.com",
              "client_type": 3
            }
          ]
        }
      }
    },
    {
      "client_info": {
        "mobilesdk_app_id": "1:289654257017:android:23143f27ce277d8f75eba8",
        "android_client_info": {
          "package_name": "au.scottmann.myapplicationauth"
        }
      },
      "oauth_client": [
        {
          "client_id": "289654257017-9jlnjiqgn96tplctpl0rnkorhskrbih8.apps.googleusercontent.com",
          "client_type": 3
        }
      ],
      "api_key": [
        {
          "current_key": "AIzaSyAVQq0eAyNp09URHcm06k_2yTqjCoHzghs"
        }
      ],
      "services": {
        "appinvite_service": {
          "other_platform_oauth_client": [
            {
              "client_id": "289654257017-79sav079jaba2ovb6c2kuql2fb7m9kb0.apps.googleusercontent.com",
              "client_type": 3
            }
          ]
        }
      }
    },
    {
      "client_info": {
        "mobilesdk_app_id": "1:289654257017:android:3b240d90f0a1836775eba8",
        "android_client_info": {
          "package_name": "au.scottmann.myfirestoreproject"
        }
      },
      "oauth_client": [
        {
          "client_id": "289654257017-9jlnjiqgn96tplctpl0rnkorhskrbih8.apps.googleusercontent.com",
          "client_type": 3
        }
      ],
      "api_key": [
        {
          "current_key": "AIzaSyAVQq0eAyNp09URHcm06k_2yTqjCoHzghs"
        }
      ],
      "services": {
        "appinvite_service": {
          "other_platform_oauth_client": [
            {
              "client_id": "289654257017-79sav079jaba2ovb6c2kuql2fb7m9kb0.apps.googleusercontent.com",
              "client_type": 3
            }
          ]
        }
      }
    },
    {
      "client_info": {
        "mobilesdk_app_id": "1:289654257017:android:4a024bc575e90e8c75eba8",
        "android_client_info": {
          "package_name": "com.example.firebasedemo"
        }
      },
      "oauth_client": [
        {
          "client_id": "289654257017-9jlnjiqgn96tplctpl0rnkorhskrbih8.apps.googleusercontent.com",
          "client_type": 3
        }
      ],
      "api_key": [
        {
          "current_key": "AIzaSyAVQq0eAyNp09URHcm06k_2yTqjCoHzghs"
        }
      ],
      "services": {
        "appinvite_service": {
          "other_platform_oauth_client": [
            {
              "client_id": "289654257017-79sav079jaba2ovb6c2kuql2fb7m9kb0.apps.googleusercontent.com",
              "client_type": 3
            }
          ]
        }
      }
    }
  ],
  "configuration_version": "1"
}